Metadata-Version: 2.1
Name: record-oc
Version: 1.0.0
Summary: Provides abstract classes meant to represent record data as Define Node types
Home-page: https://ouroboroscoding.com/record
Author: Chris Nasr - Ouroboros Coding Inc.
Author-email: chris@ouroboroscoding.com
License: MIT
Project-URL: Documentation, https://ouroboroscoding.com/record
Project-URL: Source, https://github.com/ouroboroscoding/record-python
Project-URL: Tracker, https://github.com/ouroboroscoding/record-python/issues
Keywords: data,define,database,db,sql,nosql
Platform: UNKNOWN
Requires-Python: >=3.10
License-File: LICENSE
